flask_requests_session/__init__.py
flask_requests_session-0.1.0.dist-info/METADATA
flask_requests_session-0.1.0.dist-info/WHEEL
flask_requests_session-0.1.0.dist-info/RECORD
