Metadata-Version: 2.3
Name: flask-requests-session
Version: 0.1.0
Summary: requests session extension for flask
Author: codeif
Author-email: me@codeif.com
Requires-Python: >=3.10
Classifier: Programming Language :: Python :: 3
Classifier: Programming Language :: Python :: 3.10
Classifier: Programming Language :: Python :: 3.11
Classifier: Programming Language :: Python :: 3.12
Classifier: Programming Language :: Python :: 3.13
Requires-Dist: flask (>=0.0.0)
Requires-Dist: requests (>=0.0.0)
